{
  "ok": true,
  "result": [
    {
      "update_id": 292124427,
      "message": {
        "message_id": 4,
        "from": {
          "id": 1337,
          "is_bot": false,
          "first_name": "Nickolas",
          "last_name": "F.",
          "username": "nickolasfox",
          "language_code": "ru"
        },
        "chat": {
          "id": 1337,
          "first_name": "Nickolas",
          "last_name": "F.",
          "username": "nickolasfox",
          "type": "private"
        },
        "date": 1601144749,
        "text": "/start",
        "entities": [
          {
            "offset": 0,
            "length": 6,
            "type": "bot_command"
          }
        ]
      }
    },
    {
      "update_id": 292124441,
      "inline_query": {
        "id": "600597104173276265",
        "from": {
          "id": 1337,
          "is_bot": false,
          "first_name": "Nickolas",
          "last_name": "F.",
          "username": "nickolasfox",
          "language_code": "ru"
        },
        "query": "",
        "offset": ""
      }
    },
    {
      "update_id": 292124442,
      "inline_query": {
        "id": "600597103918792144",
        "from": {
          "id": 1337,
          "is_bot": false,
          "first_name": "Nickolas",
          "last_name": "F.",
          "username": "nickolasfox",
          "language_code": "ru"
        },
        "query": "come get some",
        "offset": ""
      }
    }
  ]
}
